AUTHORS.rst
CONTRIBUTING.rst
HISTORY.rst
LICENSE
MANIFEST.in
README.rst
setup.py
django_popcorn.egg-info/PKG-INFO
django_popcorn.egg-info/SOURCES.txt
django_popcorn.egg-info/dependency_links.txt
django_popcorn.egg-info/not-zip-safe
django_popcorn.egg-info/requires.txt
django_popcorn.egg-info/top_level.txt
popcorn/__init__.py
popcorn/context_processors.py
popcorn/models.py
popcorn/utils.py
popcorn/viewmixins.py
popcorn/.ropeproject/config.py
popcorn/static/js/popcorn.js
popcorn/templates/popcorn/base.html
popcorn/templates/popcorn/form.html
popcorn/templates/popcorn/link.html
popcorn/templates/popcorn/popcorn.html
popcorn/templatetags/__init__.py
popcorn/templatetags/popcorn.py
popcorn/templatetags/.ropeproject/config.py
popcorn/test_project/manage.py
popcorn/test_project/bookstore/__init__.py
popcorn/test_project/bookstore/admin.py
popcorn/test_project/bookstore/models.py
popcorn/test_project/bookstore/tests.py
popcorn/test_project/bookstore/.ropeproject/config.py
popcorn/test_project/bookstore/templates/base.html
popcorn/test_project/bookstore/templates/bookstore/book_form.html
popcorn/test_project/test_project/__init__.py
popcorn/test_project/test_project/settings.py
popcorn/test_project/test_project/urls.py
popcorn/test_project/test_project/wsgi.py
popcorn/test_project/test_project/.ropeproject/config.py