Metadata-Version: 1.1
Name: django-popcorn
Version: 1.0.0
Summary: Add-another pop-ups a la django-admin.
Home-page: https://github.com/alixedi/django_popcorn
Author: Ali Zaidi
Author-email: alixedi@gmail.com
License: BSD
Keywords: django_popcorn
Platform: UNKNOWN
Classifier: Development Status :: 2 - Pre-Alpha
Classifier: Framework :: Django
Classifier: Intended Audience :: Developers
Classifier: License :: OSI Approved :: BSD License
Classifier: Natural Language :: English
Classifier: Programming Language :: Python :: 2
Classifier: Programming Language :: Python :: 2.6
Classifier: Programming Language :: Python :: 2.7
Classifier: Programming Language :: Python :: 3
Classifier: Programming Language :: Python :: 3.3
